sideload_Beekeeper_Studio_4_bin_67447fbee41b4d34e45a4af9/Beekeeper-Studio-4.6.8-portable.exe
sideload_Beekeeper_Studio_4_bin_67447fbee41b4d34e45a4af9/__init__.py
sideload_Beekeeper_Studio_4_bin_67447fbee41b4d34e45a4af9-1.0.0.dist-info/METADATA
sideload_Beekeeper_Studio_4_bin_67447fbee41b4d34e45a4af9-1.0.0.dist-info/WHEEL
sideload_Beekeeper_Studio_4_bin_67447fbee41b4d34e45a4af9-1.0.0.dist-info/top_level.txt
sideload_Beekeeper_Studio_4_bin_67447fbee41b4d34e45a4af9-1.0.0.dist-info/RECORD
