Metadata-Version: 2.1
Name: sideload_Beekeeper_Studio_4_bin_67447fbee41b4d34e45a4af9
Version: 1.0.0
Summary: Sideloaded package
Author: Null Void
Requires-Python: >=3.8
